jeffs_ds/__init__.py
jeffs_ds/jeffs_ds.py
jeffs_ds-0.1.0.dist-info/AUTHORS.rst
jeffs_ds-0.1.0.dist-info/LICENSE
jeffs_ds-0.1.0.dist-info/METADATA
jeffs_ds-0.1.0.dist-info/WHEEL
jeffs_ds-0.1.0.dist-info/top_level.txt
jeffs_ds-0.1.0.dist-info/RECORD
