Metadata-Version: 2.1
Name: jeffs-ds
Version: 0.1.0
Summary: Common packages Jeff uses 
Home-page: https://github.com/sik-flow/jeffs_ds
Author: Jeff Herman
Author-email: jherman1199@gmail.com
License: GNU General Public License v3
Keywords: jeffs_ds
Platform: UNKNOWN
Classifier: Development Status :: 2 - Pre-Alpha
Classifier: Intended Audience :: Developers
Classifier: License :: OSI Approved :: GNU General Public License v3 (GPLv3)
Classifier: Natural Language :: English
Classifier: Programming Language :: Python :: 3
Classifier: Programming Language :: Python :: 3.5
Classifier: Programming Language :: Python :: 3.6
Classifier: Programming Language :: Python :: 3.7
Classifier: Programming Language :: Python :: 3.8
Requires-Python: >=3.5
